block_finder/__init__.py
block_finder/blockfinder.py
block_finder/test.py
blockfinder-4.0.0.dist-info/DESCRIPTION.rst
blockfinder-4.0.0.dist-info/METADATA
blockfinder-4.0.0.dist-info/RECORD
blockfinder-4.0.0.dist-info/WHEEL
blockfinder-4.0.0.dist-info/entry_points.txt
blockfinder-4.0.0.dist-info/metadata.json
blockfinder-4.0.0.dist-info/pbr.json
blockfinder-4.0.0.dist-info/top_level.txt
