Metadata-Version: 2.0
Name: blockfinder
Version: 4.0.0
Summary: Blockfinder enumerates network information for countries.
Home-page: https://github.com/ioerror/blockfinder
Author: David
Author-email: db@d1b.org
License: BSD
Platform: UNKNOWN
Classifier: Development Status :: 4 - Beta
Classifier: Environment :: Console
Classifier: Intended Audience :: Developers
Classifier: Operating System :: OS Independent
Classifier: Programming Language :: Python
Classifier: Programming Language :: Python :: 2.6
Classifier: Programming Language :: Python :: 2.7
Classifier: Programming Language :: Python :: 3
Classifier: Programming Language :: Python :: 3.3
Classifier: Programming Language :: Python :: 3.4
Classifier: Programming Language :: Python :: 3.5
Classifier: License :: OSI Approved :: BSD License
Requires-Dist: py2-ipaddress (==3.4.1)
